aps_perimeter.py
aps_perimeter-0.0.1.dist-info/LICENSE.txt
aps_perimeter-0.0.1.dist-info/METADATA
aps_perimeter-0.0.1.dist-info/WHEEL
aps_perimeter-0.0.1.dist-info/top_level.txt
aps_perimeter-0.0.1.dist-info/RECORD
